pyinputlib/__init__.py
pyinputlib-0.0.2.dist-info/METADATA
pyinputlib-0.0.2.dist-info/WHEEL
pyinputlib-0.0.2.dist-info/top_level.txt
pyinputlib-0.0.2.dist-info/RECORD
